fosslight_dependency/__init__.py
fosslight_dependency/_analyze_dependency.py
fosslight_dependency/_graph_convertor.py
fosslight_dependency/_help.py
fosslight_dependency/_package_manager.py
fosslight_dependency/cli.py
fosslight_dependency/constant.py
fosslight_dependency/dependency_item.py
fosslight_dependency/run_dependency_scanner.py
fosslight_dependency/LICENSES/LICENSE
fosslight_dependency/LICENSES/LicenseRef-3rd_party_licenses.txt
fosslight_dependency/package_manager/Android.py
fosslight_dependency/package_manager/Cargo.py
fosslight_dependency/package_manager/Carthage.py
fosslight_dependency/package_manager/Cocoapods.py
fosslight_dependency/package_manager/Go.py
fosslight_dependency/package_manager/Gradle.py
fosslight_dependency/package_manager/Helm.py
fosslight_dependency/package_manager/Maven.py
fosslight_dependency/package_manager/Npm.py
fosslight_dependency/package_manager/Nuget.py
fosslight_dependency/package_manager/Pnpm.py
fosslight_dependency/package_manager/Pub.py
fosslight_dependency/package_manager/Pypi.py
fosslight_dependency/package_manager/Swift.py
fosslight_dependency/package_manager/Unity.py
fosslight_dependency/package_manager/Yarn.py
fosslight_dependency/package_manager/__init__.py
fosslight_dependency-4.1.31.dist-info/licenses/LICENSE
fosslight_dependency-4.1.31.dist-info/licenses/LICENSES/Apache-2.0.txt
fosslight_dependency-4.1.31.dist-info/licenses/LICENSES/LicenseRef-3rd_party_licenses.txt
fosslight_dependency-4.1.31.dist-info/licenses/LICENSES/MIT.txt
fosslight_dependency-4.1.31.dist-info/METADATA
fosslight_dependency-4.1.31.dist-info/WHEEL
fosslight_dependency-4.1.31.dist-info/entry_points.txt
fosslight_dependency-4.1.31.dist-info/top_level.txt
fosslight_dependency-4.1.31.dist-info/RECORD
