Metadata-Version: 2.4
Name: fosslight_dependency
Version: 4.1.31
Summary: FOSSLight Dependency Scanner
Home-page: https://github.com/fosslight/fosslight_dependency_scanner
Download-URL: https://github.com/fosslight/fosslight_dependency_scanner
Author: LG Electronics
License: Apache-2.0
Classifier: License :: OSI Approved :: Apache Software License
Classifier: Programming Language :: Python :: 3
Classifier: Programming Language :: Python :: 3.10
Classifier: Programming Language :: Python :: 3.11
Classifier: Programming Language :: Python :: 3.12
Requires-Python: >=3.10,<3.13
License-File: LICENSE
License-File: LICENSES/Apache-2.0.txt
License-File: LICENSES/LicenseRef-3rd_party_licenses.txt
License-File: LICENSES/MIT.txt
Requires-Dist: openpyxl
Requires-Dist: beautifulsoup4
Requires-Dist: lxml
Requires-Dist: virtualenv
Requires-Dist: pyyaml
Requires-Dist: lastversion
Requires-Dist: fosslight_util>=2.1.37
Requires-Dist: PyGithub
Requires-Dist: requirements-parser
Requires-Dist: defusedxml
Requires-Dist: packageurl-python
Requires-Dist: igraph
Requires-Dist: matplotlib
Requires-Dist: pyaskalono
Dynamic: author
Dynamic: classifier
Dynamic: description
Dynamic: description-content-type
Dynamic: download-url
Dynamic: home-page
Dynamic: license
Dynamic: license-file
Dynamic: requires-dist
Dynamic: requires-python
Dynamic: summary
